torchsketch/__init__.py
torchsketch/data/__init__.py
torchsketch/data/dataloaders/__init__.py
torchsketch/data/dataloaders/qmul_chair/__init__.py
torchsketch/data/dataloaders/qmul_chair/qmul_chair.py
torchsketch/data/dataloaders/qmul_shoe/__init__.py
torchsketch/data/dataloaders/qmul_shoe/qmul_shoe.py
torchsketch/data/dataloaders/quickdraw/__init__.py
torchsketch/data/dataloaders/quickdraw/quickdraw_414k/__init__.py
torchsketch/data/dataloaders/quickdraw/quickdraw_414k/quickdraw414k_4_cnn.py
torchsketch/data/dataloaders/quickdraw/quickdraw_414k/quickdraw414k_4_multigraph_transformer.py
torchsketch/data/dataloaders/quickdraw/quickdraw_414k/quickdraw414k_4_rnn.py
torchsketch/data/dataloaders/quickdraw/quickdraw_414k/quickdraw414k_4_tcn.py
torchsketch/data/dataloaders/quickdraw/quickdraw_414k/quickdraw414k_4_vanilla_transformer.py
torchsketch/data/dataloaders/tu_berlin/__init__.py
torchsketch/data/dataloaders/tu_berlin/tu_berlin.py
torchsketch/data/datasets/__init__.py
torchsketch/data/datasets/qmul_chair/__init__.py
torchsketch/data/datasets/qmul_chair/download_qmul_chair.py
torchsketch/data/datasets/qmul_shoe/__init__.py
torchsketch/data/datasets/qmul_shoe/download_qmul_shoe.py
torchsketch/data/datasets/quickdraw/__init__.py
torchsketch/data/datasets/quickdraw/quickdraw_414k/__init__.py
torchsketch/data/datasets/quickdraw/quickdraw_414k/download_quickdraw_414k.py
torchsketch/data/datasets/sketchy/__init__.py
torchsketch/data/datasets/sketchy/download_sketchy.py
torchsketch/data/datasets/tu_berlin/__init__.py
torchsketch/data/datasets/tu_berlin/download_tu_berlin.py
torchsketch/networks/__init__.py
torchsketch/networks/cnn/__init__.py
torchsketch/networks/gnn/__init__.py
torchsketch/networks/gnn/graph_attention_network/__init__.py
torchsketch/networks/gnn/graph_attention_network/graph_attention_network.py
torchsketch/networks/gnn/graph_attention_network/graph_transformer_layer.py
torchsketch/networks/gnn/graph_convolutional_network/__init__.py
torchsketch-0.1.0.dist-info/LICENSE
torchsketch-0.1.0.dist-info/METADATA
torchsketch-0.1.0.dist-info/WHEEL
torchsketch-0.1.0.dist-info/top_level.txt
torchsketch-0.1.0.dist-info/RECORD
