Metadata-Version: 2.1
Name: torchsketch
Version: 0.1.0
Summary: TorchSketch is an open source software library for free-hand sketch oriented deep learning research, which is built on the top of PyTorch.
Home-page: https://github.com/PengBoXiangShang/torchsketch/
Author: Peng Xu
Author-email: peng.xu@bupt.edu.cn
License: MIT
Keywords: sketch,free-hand sketch,pytorch,deep learning
Platform: UNKNOWN
Classifier: Programming Language :: Python :: 3
Classifier: Programming Language :: Python :: 3.7
Classifier: License :: OSI Approved :: MIT License
Requires-Dist: torchvision (==0.4.0)
Requires-Dist: torchnet (==0.0.4)
Requires-Dist: torch (==1.2.0)
Requires-Dist: Pillow (<7.0.0)
Requires-Dist: gdown
Requires-Dist: pdf2image
Requires-Dist: pyfiglet
Requires-Dist: pyunpack
Requires-Dist: scipy
Requires-Dist: wget
Requires-Dist: CairoSVG
Requires-Dist: numpy
Requires-Dist: imageio
Requires-Dist: patool
